README.rst
setup.py
mlab.egg-info/PKG-INFO
mlab.egg-info/SOURCES.txt
mlab.egg-info/dependency_links.txt
mlab.egg-info/top_level.txt
src/mlab/__init__.py
src/mlab/awmstools.py
src/mlab/matlabcom.py
src/mlab/matlabpipe.py
src/mlab/mlabraw.py
src/mlab/mlabwrap.py